{
  "generatedAt": "2026-03-24T01:14:59.122Z",
  "podcast": {
    "title": "Norm Macdonald Live",
    "subtitle": "The complete 39-episode run of Norm Macdonald Live",
    "author": "Norm Macdonald",
    "publisher": "Video Podcast Network / JASH",
    "description": "Norm Macdonald and Adam Eget welcome comedians, actors, and friends for long-form conversations.",
    "genres": [
      "Comedy",
      "Talk Show",
      "Interview"
    ],
    "tags": [
      "norm-macdonald",
      "norm-macdonald-live",
      "comedy",
      "interview",
      "archive"
    ],
    "releaseDate": "2013-03-26",
    "language": "en",
    "explicit": true,
    "type": "episodic",
    "cover": "https://upload.wikimedia.org/wikipedia/en/2/22/Norm_Macdonald_Live.jpg",
    "itunesId": "625135046",
    "itunesPageUrl": "https://itunes.apple.com/us/podcast/norm-macdonald-live/id625135046",
    "feedUrl": "http://localhost:8042/rss/norm-macdonald-live.xml",
    "source": {
      "archiveList": "https://normmacdonaldarchive.com/nml",
      "wikipedia": "https://en.wikipedia.org/wiki/Norm_Macdonald_Live",
      "imdbEpisodes": "https://www.imdb.com/title/tt6407712/episodes/"
    }
  },
  "episodes": [
    {
      "slug": "s1-e1-bob-einstein-",
      "guid": "nml-s1-e1-bob-einstein-",
      "season": 1,
      "episodeNumber": 1,
      "title": "Bob Einstein (Super Dave Osborne)",
      "guest": "Bob Einstein (Super Dave Osborne)",
      "releaseDate": "2013-03-26",
      "description": "The premiere episode of Norm Macdonald Live, with guest Super Dave.",
      "pageUrl": "https://normmacdonaldarchive.com/nml/s1-e1-bob-einstein-",
      "mediaUrl": "https://archive.org/download/Norm_Macdonald_Live/Norm%20Macdonald%20Live%20-%20S01E01%20-%20Norm%20Macdonald%20with%20Guest%20Bob%20Einstein%20(Super%20Dave%20Osborne).mp4",
      "embedUrl": "https://archive.org/embed/Norm_Macdonald_Live/Norm%20Macdonald%20Live%20-%20S01E01%20-%20Norm%20Macdonald%20with%20Guest%20Super%20Dave%20Osborne.mp4",
      "thumbnail": "https://upload.wikimedia.org/wikipedia/en/2/22/Norm_Macdonald_Live.jpg",
      "tags": [
        "season-1",
        "norm-macdonald-live",
        "Bob Einstein (Super Dave Osborne)"
      ],
      "friendlyTitle": "S1.E1 · Super Dave",
      "publishedDate": "2013-03-26",
      "fileTitle": "Norm Macdonald Live - S01E01 - Norm Macdonald with Guest Bob Einstein (Super Dave Osborne)",
      "episodeOverall": 1
    },
    {
      "slug": "s1-e2-tom-green",
      "guid": "nml-s1-e2-tom-green",
      "season": 1,
      "episodeNumber": 2,
      "title": "Tom Green",
      "guest": "Tom Green",
      "releaseDate": "2013-04-02",
      "description": "Norm Macdonald and Adam Eget welcome Tom Green to the show.",
      "pageUrl": "https://normmacdonaldarchive.com/nml/s1-e2-tom-green",
      "mediaUrl": "https://archive.org/download/Norm_Macdonald_Live/Norm%20Macdonald%20Live%20-%20S01E02%20-%20Norm%20Macdonald%20with%20Guest%20Tom%20Green.mp4",
      "embedUrl": "https://archive.org/embed/Norm_Macdonald_Live/Norm%20Macdonald%20Live%20-%20S01E02%20-%20Norm%20Macdonald%20with%20Guest%20Tom%20Green.mp4",
      "thumbnail": "https://upload.wikimedia.org/wikipedia/en/2/22/Norm_Macdonald_Live.jpg",
      "tags": [
        "season-1",
        "norm-macdonald-live",
        "Tom Green"
      ],
      "friendlyTitle": "S1.E2 · Tom Green",
      "publishedDate": "2013-04-02",
      "fileTitle": "Norm Macdonald Live - S01E02 - Norm Macdonald with Guest Tom Green",
      "episodeOverall": 2
    },
    {
      "slug": "s1-e3-fred-stoller",
      "guid": "nml-s1-e3-fred-stoller",
      "season": 1,
      "episodeNumber": 3,
      "title": "Fred Stoller",
      "guest": "Fred Stoller",
      "releaseDate": "2013-04-09",
      "description": "Norm Macdonald and Adam Eget welcome Fred Stoller to the show.",
      "pageUrl": "https://normmacdonaldarchive.com/nml/s1-e3-fred-stoller",
      "mediaUrl": "https://archive.org/download/Norm_Macdonald_Live/Norm%20Macdonald%20Live%20-%20S01E03%20-%20Norm%20Macdonald%20with%20Guest%20Fred%20Stoller.mp4",
      "embedUrl": "https://archive.org/embed/Norm_Macdonald_Live/Norm%20Macdonald%20Live%20-%20S01E03%20-%20Norm%20Macdonald%20with%20Guest%20Fred%20Stoller.mp4",
      "thumbnail": "https://upload.wikimedia.org/wikipedia/en/2/22/Norm_Macdonald_Live.jpg",
      "tags": [
        "season-1",
        "norm-macdonald-live",
        "Fred Stoller"
      ],
      "friendlyTitle": "S1.E3 · Fred Stoller",
      "publishedDate": "2013-04-09",
      "fileTitle": "Norm Macdonald Live - S01E03 - Norm Macdonald with Guest Fred Stoller",
      "episodeOverall": 3
    },
    {
      "slug": "s1-e4-russell-brand",
      "guid": "nml-s1-e4-russell-brand",
      "season": 1,
      "episodeNumber": 4,
      "title": "Russell Brand",
      "guest": "Russell Brand",
      "releaseDate": "2013-04-16",
      "description": "Norm Macdonald and Adam Eget welcome Russell Brand to the show.",
      "pageUrl": "https://normmacdonaldarchive.com/nml/s1-e4-russell-brand",
      "mediaUrl": "https://archive.org/download/Norm_Macdonald_Live/Norm%20Macdonald%20Live%20-%20S01E04%20-%20Norm%20Macdonald%20with%20Guest%20Russell%20Brand.mp4",
      "embedUrl": "https://archive.org/embed/Norm_Macdonald_Live/Norm%20Macdonald%20Live%20-%20S01E04%20-%20Norm%20Macdonald%20with%20Guest%20Russell%20Brand.mp4",
      "thumbnail": "https://upload.wikimedia.org/wikipedia/en/2/22/Norm_Macdonald_Live.jpg",
      "tags": [
        "season-1",
        "norm-macdonald-live",
        "Russell Brand"
      ],
      "friendlyTitle": "S1.E4 · Russell Brand",
      "publishedDate": "2013-04-16",
      "fileTitle": "Norm Macdonald Live - S01E04 - Norm Macdonald with Guest Russell Brand",
      "episodeOverall": 4
    },
    {
      "slug": "s1-e5-billy-bob-thornton",
      "guid": "nml-s1-e5-billy-bob-thornton",
      "season": 1,
      "episodeNumber": 5,
      "title": "Billy Bob Thornton",
      "guest": "Billy Bob Thornton",
      "releaseDate": "2013-04-23",
      "description": "Norm Macdonald and Adam Eget welcome Billy Bob Thornton to the show.",
      "pageUrl": "https://normmacdonaldarchive.com/nml/s1-e5-billy-bob-thornton",
      "mediaUrl": "https://archive.org/download/Norm_Macdonald_Live/Norm%20Macdonald%20Live%20-%20S01E05%20-%20Norm%20Macdonald%20with%20Guest%20Billy%20Bob%20Thornton.mp4",
      "embedUrl": "https://archive.org/embed/Norm_Macdonald_Live/Norm%20Macdonald%20Live%20-%20S01E05%20-%20Norm%20Macdonald%20with%20Guest%20Billy%20Bob%20Thornton.mp4",
      "thumbnail": "https://upload.wikimedia.org/wikipedia/en/2/22/Norm_Macdonald_Live.jpg",
      "tags": [
        "season-1",
        "norm-macdonald-live",
        "Billy Bob Thornton"
      ],
      "friendlyTitle": "S1.E5 · Billy Bob Thornton",
      "publishedDate": "2013-04-23",
      "fileTitle": "Norm Macdonald Live - S01E05 - Norm Macdonald with Guest Billy Bob Thornton",
      "episodeOverall": 5
    },
    {
      "slug": "s1-e6-larry-king",
      "guid": "nml-s1-e6-larry-king",
      "season": 1,
      "episodeNumber": 6,
      "title": "Larry King",
      "guest": "Larry King",
      "releaseDate": "2013-04-30",
      "description": "Norm Macdonald and Adam Eget welcome Larry King to the show.",
      "pageUrl": "https://normmacdonaldarchive.com/nml/s1-e6-larry-king",
      "mediaUrl": "https://archive.org/download/Norm_Macdonald_Live/Norm%20Macdonald%20Live%20-%20S01E06%20-%20Norm%20Macdonald%20with%20Guest%20Larry%20King.mp4",
      "embedUrl": "https://archive.org/embed/Norm_Macdonald_Live/Norm%20Macdonald%20Live%20-%20S01E06%20-%20Norm%20Macdonald%20with%20Guest%20Larry%20King.mp4",
      "thumbnail": "https://upload.wikimedia.org/wikipedia/en/2/22/Norm_Macdonald_Live.jpg",
      "tags": [
        "season-1",
        "norm-macdonald-live",
        "Larry King"
      ],
      "friendlyTitle": "S1.E6 · Larry King",
      "publishedDate": "2013-04-30",
      "fileTitle": "Norm Macdonald Live - S01E06 - Norm Macdonald with Guest Larry King",
      "episodeOverall": 6
    },
    {
      "slug": "s1-e7-kevin-nealon",
      "guid": "nml-s1-e7-kevin-nealon",
      "season": 1,
      "episodeNumber": 7,
      "title": "Kevin Nealon",
      "guest": "Kevin Nealon",
      "releaseDate": "2013-05-07",
      "description": "Norm Macdonald and Adam Eget welcome Kevin Nealon to the show.",
      "pageUrl": "https://normmacdonaldarchive.com/nml/s1-e7-kevin-nealon",
      "mediaUrl": "https://archive.org/download/Norm_Macdonald_Live/Norm%20Macdonald%20Live%20-%20S01E07%20-%20Norm%20Macdonald%20with%20Guest%20Kevin%20Nealon.mp4",
      "embedUrl": "https://archive.org/embed/Norm_Macdonald_Live/Norm%20Macdonald%20Live%20-%20S01E07%20-%20Norm%20Macdonald%20with%20Guest%20Kevin%20Nealon.mp4",
      "thumbnail": "https://upload.wikimedia.org/wikipedia/en/2/22/Norm_Macdonald_Live.jpg",
      "tags": [
        "season-1",
        "norm-macdonald-live",
        "Kevin Nealon"
      ],
      "friendlyTitle": "S1.E7 · Kevin Nealon",
      "publishedDate": "2013-05-07",
      "fileTitle": "Norm Macdonald Live - S01E07 - Norm Macdonald with Guest Kevin Nealon",
      "episodeOverall": 7
    },
    {
      "slug": "s1-e8-simon-helberg",
      "guid": "nml-s1-e8-simon-helberg",
      "season": 1,
      "episodeNumber": 8,
      "title": "Simon Helberg",
      "guest": "Simon Helberg",
      "releaseDate": "2013-05-14",
      "description": "Norm Macdonald and Adam Eget welcome Simon Helberg to the show.",
      "pageUrl": "https://normmacdonaldarchive.com/nml/s1-e8-simon-helberg",
      "mediaUrl": "https://archive.org/download/Norm_Macdonald_Live/Norm%20Macdonald%20Live%20-%20S01E08%20-%20Norm%20Macdonald%20with%20Guest%20Simon%20Helberg.mp4",
      "embedUrl": "https://archive.org/embed/Norm_Macdonald_Live/Norm%20Macdonald%20Live%20-%20S01E08%20-%20Norm%20Macdonald%20with%20Guest%20Simon%20Helberg.mp4",
      "thumbnail": "https://upload.wikimedia.org/wikipedia/en/2/22/Norm_Macdonald_Live.jpg",
      "tags": [
        "season-1",
        "norm-macdonald-live",
        "Simon Helberg"
      ],
      "friendlyTitle": "S1.E8 · Simon Helberg",
      "publishedDate": "2013-05-14",
      "fileTitle": "Norm Macdonald Live - S01E08 - Norm Macdonald with Guest Simon Helberg",
      "episodeOverall": 8
    },
    {
      "slug": "s1-e9-nick-swardson",
      "guid": "nml-s1-e9-nick-swardson",
      "season": 1,
      "episodeNumber": 9,
      "title": "Nick Swardson",
      "guest": "Nick Swardson",
      "releaseDate": "2013-05-21",
      "description": "Norm Macdonald and Adam Eget welcome Nick Swardson to the show.",
      "pageUrl": "https://normmacdonaldarchive.com/nml/s1-e9-nick-swardson",
      "mediaUrl": "https://archive.org/download/Norm_Macdonald_Live/Norm%20Macdonald%20Live%20-%20S01E09%20-%20Norm%20Macdonald%20with%20Guest%20Nick%20Swardson.mp4",
      "embedUrl": "https://archive.org/embed/Norm_Macdonald_Live/Norm%20Macdonald%20Live%20-%20S01E09%20-%20Norm%20Macdonald%20with%20Guest%20Nick%20Swardson.mp4",
      "thumbnail": "https://upload.wikimedia.org/wikipedia/en/2/22/Norm_Macdonald_Live.jpg",
      "tags": [
        "season-1",
        "norm-macdonald-live",
        "Nick Swardson"
      ],
      "friendlyTitle": "S1.E9 · Nick Swardson",
      "publishedDate": "2013-05-21",
      "fileTitle": "Norm Macdonald Live - S01E09 - Norm Macdonald with Guest Nick Swardson",
      "episodeOverall": 9
    },
    {
      "slug": "s1-e10-andy-dick",
      "guid": "nml-s1-e10-andy-dick",
      "season": 1,
      "episodeNumber": 10,
      "title": "Andy Dick",
      "guest": "Andy Dick",
      "releaseDate": "2013-05-27",
      "description": "Norm Macdonald and Adam Eget welcome Andy Dick to the show.",
      "pageUrl": "https://normmacdonaldarchive.com/nml/s1-e10-andy-dick",
      "mediaUrl": "https://archive.org/download/Norm_Macdonald_Live/Norm%20Macdonald%20Live%20-%20S01E10%20-%20Norm%20Macdonald%20with%20Guest%20Andy%20Dick.mp4",
      "embedUrl": "https://archive.org/embed/Norm_Macdonald_Live/Norm%20Macdonald%20Live%20-%20S01E10%20-%20Norm%20Macdonald%20with%20Guest%20Andy%20Dick.mp4",
      "thumbnail": "https://upload.wikimedia.org/wikipedia/en/2/22/Norm_Macdonald_Live.jpg",
      "tags": [
        "season-1",
        "norm-macdonald-live",
        "Andy Dick"
      ],
      "friendlyTitle": "S1.E10 · Andy Dick",
      "publishedDate": "2013-05-27",
      "fileTitle": "Norm Macdonald Live - S01E10 - Norm Macdonald with Guest Andy Dick",
      "episodeOverall": 10
    },
    {
      "slug": "s1-e11-gilbert-gottfried-",
      "guid": "nml-s1-e11-gilbert-gottfried-",
      "season": 1,
      "episodeNumber": 11,
      "title": "Gilbert Gottfried (Part 1)",
      "guest": "Gilbert Gottfried (Part 1)",
      "releaseDate": "2013-06-11",
      "description": "The first part of Norm Macdonald's sit down with Gilbert Gottfried.",
      "pageUrl": "https://normmacdonaldarchive.com/nml/s1-e11-gilbert-gottfried-",
      "mediaUrl": "https://archive.org/download/Norm_Macdonald_Live/Norm%20Macdonald%20Live%20-%20S01E11%20-%20Norm%20Macdonald%20with%20Guest%20Gilbert%20Gottfried%20(Part%201).mp4",
      "embedUrl": "https://archive.org/embed/Norm_Macdonald_Live/Norm%20Macdonald%20Live%20-%20S01E11%20-%20Norm%20Macdonald%20with%20Guest%20Gilbert%20Gottfried%20(Pt%201).mp4",
      "thumbnail": "https://upload.wikimedia.org/wikipedia/en/2/22/Norm_Macdonald_Live.jpg",
      "tags": [
        "season-1",
        "norm-macdonald-live",
        "Gilbert Gottfried (Part 1)"
      ],
      "friendlyTitle": "S1.E11 · Gilbert Gottfried Pt. 1",
      "publishedDate": "2013-06-11",
      "fileTitle": "Norm Macdonald Live - S01E11 - Norm Macdonald with Guest Gilbert Gottfried (Part 1)",
      "episodeOverall": 11
    },
    {
      "slug": "s1-e12-gilbert-gottfried-",
      "guid": "nml-s1-e12-gilbert-gottfried-",
      "season": 1,
      "episodeNumber": 12,
      "title": "Gilbert Gottfried (Part 2)",
      "guest": "Gilbert Gottfried (Part 2)",
      "releaseDate": "2013-06-17",
      "description": "The second part of Norm Macdonald's sit down with Gilbert Gottfried.",
      "pageUrl": "https://normmacdonaldarchive.com/nml/s1-e12-gilbert-gottfried-",
      "mediaUrl": "https://archive.org/download/Norm_Macdonald_Live/Norm%20Macdonald%20Live%20-%20S01E12%20-%20Norm%20Macdonald%20with%20Guest%20Gilbert%20Gottfried%20(Part%202).mp4",
      "embedUrl": "https://archive.org/embed/Norm_Macdonald_Live/Norm%20Macdonald%20Live%20-%20S01E12%20-%20Norm%20Macdonald%20with%20Guest%20Gilbert%20Gottfried%20(Pt%202).mp4",
      "thumbnail": "https://upload.wikimedia.org/wikipedia/en/2/22/Norm_Macdonald_Live.jpg",
      "tags": [
        "season-1",
        "norm-macdonald-live",
        "Gilbert Gottfried (Part 2)"
      ],
      "friendlyTitle": "S1.E12 · Gilbert Gottfried Pt. 2",
      "publishedDate": "2013-06-17",
      "fileTitle": "Norm Macdonald Live - S01E12 - Norm Macdonald with Guest Gilbert Gottfried (Part 2)",
      "episodeOverall": 12
    },
    {
      "slug": "s2-e1-ray-romano",
      "guid": "nml-s2-e1-ray-romano",
      "season": 2,
      "episodeNumber": 1,
      "title": "Ray Romano",
      "guest": "Ray Romano",
      "releaseDate": "2014-05-12",
      "description": "Season 2 kicks off with 'Everybody Loves Raymond' star, Ray Romano.",
      "pageUrl": "https://normmacdonaldarchive.com/nml/s2-e1-ray-romano",
      "mediaUrl": "https://archive.org/download/Norm_Macdonald_Live/Norm%20Macdonald%20Live%20-%20S02E01%20-%20Norm%20Macdonald%20with%20Guest%20Ray%20Romano.mp4",
      "embedUrl": "https://archive.org/embed/Norm_Macdonald_Live/Norm%20Macdonald%20Live%20-%20S02E01%20-%20Norm%20Macdonald%20with%20Guest%20Ray%20Romano.mp4",
      "thumbnail": "https://upload.wikimedia.org/wikipedia/en/2/22/Norm_Macdonald_Live.jpg",
      "tags": [
        "season-2",
        "norm-macdonald-live",
        "Ray Romano"
      ],
      "friendlyTitle": "S2.E1 · Ray Romano",
      "publishedDate": "2014-05-12",
      "fileTitle": "Norm Macdonald Live - S02E01 - Norm Macdonald with Guest Ray Romano",
      "episodeOverall": 13
    },
    {
      "slug": "s2-e2-adam-sandler",
      "guid": "nml-s2-e2-adam-sandler",
      "season": 2,
      "episodeNumber": 2,
      "title": "Adam Sandler",
      "guest": "Adam Sandler",
      "releaseDate": "2014-05-21",
      "description": "Norm's close friend and comedy superstar Adam Sandler joins the show.",
      "pageUrl": "https://normmacdonaldarchive.com/nml/s2-e2-adam-sandler",
      "mediaUrl": "https://archive.org/download/Norm_Macdonald_Live/Norm%20Macdonald%20Live%20-%20S02E02%20-%20Norm%20Macdonald%20with%20Guest%20Adam%20Sandler.mp4",
      "embedUrl": "https://archive.org/embed/Norm_Macdonald_Live/Norm%20Macdonald%20Live%20-%20S02E02%20-%20Norm%20Macdonald%20with%20Guest%20Adam%20Sandler.mp4",
      "thumbnail": "https://upload.wikimedia.org/wikipedia/en/2/22/Norm_Macdonald_Live.jpg",
      "tags": [
        "season-2",
        "norm-macdonald-live",
        "Adam Sandler"
      ],
      "friendlyTitle": "S2.E2 · Adam Sandler",
      "publishedDate": "2014-05-21",
      "fileTitle": "Norm Macdonald Live - S02E02 - Norm Macdonald with Guest Adam Sandler",
      "episodeOverall": 14
    },
    {
      "slug": "s2-e3-david-spade",
      "guid": "nml-s2-e3-david-spade",
      "season": 2,
      "episodeNumber": 3,
      "title": "David Spade",
      "guest": "David Spade",
      "releaseDate": "2014-05-26",
      "description": "Fellow SNL cast member and friend David Spade sits down with Norm.",
      "pageUrl": "https://normmacdonaldarchive.com/nml/s2-e3-david-spade",
      "mediaUrl": "https://archive.org/download/Norm_Macdonald_Live/Norm%20Macdonald%20Live%20-%20S02E03%20-%20Norm%20Macdonald%20with%20Guest%20David%20Spade.mp4",
      "embedUrl": "https://archive.org/embed/Norm_Macdonald_Live/Norm%20Macdonald%20Live%20-%20S02E03%20-%20Norm%20Macdonald%20with%20Guest%20David%20Spade.mp4",
      "thumbnail": "https://upload.wikimedia.org/wikipedia/en/2/22/Norm_Macdonald_Live.jpg",
      "tags": [
        "season-2",
        "norm-macdonald-live",
        "David Spade"
      ],
      "friendlyTitle": "S2.E3 · David Spade",
      "publishedDate": "2014-05-26",
      "fileTitle": "Norm Macdonald Live - S02E03 - Norm Macdonald with Guest David Spade",
      "episodeOverall": 15
    },
    {
      "slug": "s2-e4-carl-reiner",
      "guid": "nml-s2-e4-carl-reiner",
      "season": 2,
      "episodeNumber": 4,
      "title": "Carl Reiner",
      "guest": "Carl Reiner",
      "releaseDate": "2014-06-02",
      "description": "A conversation with the absolute legend of comedy, Carl Reiner.",
      "pageUrl": "https://normmacdonaldarchive.com/nml/s2-e4-carl-reiner",
      "mediaUrl": "https://archive.org/download/Norm_Macdonald_Live/Norm%20Macdonald%20Live%20-%20S02E04%20-%20Norm%20Macdonald%20with%20Guest%20Carl%20Reiner.mp4",
      "embedUrl": "https://archive.org/embed/Norm_Macdonald_Live/Norm%20Macdonald%20Live%20-%20S02E04%20-%20Norm%20Macdonald%20with%20Guest%20Carl%20Reiner.mp4",
      "thumbnail": "https://upload.wikimedia.org/wikipedia/en/2/22/Norm_Macdonald_Live.jpg",
      "tags": [
        "season-2",
        "norm-macdonald-live",
        "Carl Reiner"
      ],
      "friendlyTitle": "S2.E4 · Carl Reiner",
      "publishedDate": "2014-06-02",
      "fileTitle": "Norm Macdonald Live - S02E04 - Norm Macdonald with Guest Carl Reiner",
      "episodeOverall": 16
    },
    {
      "slug": "s2-e5-fred-willard",
      "guid": "nml-s2-e5-fred-willard",
      "season": 2,
      "episodeNumber": 5,
      "title": "Fred Willard",
      "guest": "Fred Willard",
      "releaseDate": "2014-06-09",
      "description": "The brilliant and hilarious improviser Fred Willard joins Norm.",
      "pageUrl": "https://normmacdonaldarchive.com/nml/s2-e5-fred-willard",
      "mediaUrl": "https://archive.org/download/Norm_Macdonald_Live/Norm%20Macdonald%20Live%20-%20S02E05%20-%20Norm%20Macdonald%20with%20Guest%20Fred%20Willard.mp4",
      "embedUrl": "https://archive.org/embed/Norm_Macdonald_Live/Norm%20Macdonald%20Live%20-%20S02E05%20-%20Norm%20Macdonald%20with%20Guest%20Fred%20Willard.mp4",
      "thumbnail": "https://upload.wikimedia.org/wikipedia/en/2/22/Norm_Macdonald_Live.jpg",
      "tags": [
        "season-2",
        "norm-macdonald-live",
        "Fred Willard"
      ],
      "friendlyTitle": "S2.E5 · Fred Willard",
      "publishedDate": "2014-06-09",
      "fileTitle": "Norm Macdonald Live - S02E05 - Norm Macdonald with Guest Fred Willard",
      "episodeOverall": 17
    },
    {
      "slug": "s2-e6-todd-glass-",
      "guid": "nml-s2-e6-todd-glass-",
      "season": 2,
      "episodeNumber": 6,
      "title": "Todd Glass (Part 1)",
      "guest": "Todd Glass (Part 1)",
      "releaseDate": "2014-06-16",
      "description": "The first part of Norm Macdonald's sit down with Todd Glass.",
      "pageUrl": "https://normmacdonaldarchive.com/nml/s2-e6-todd-glass-",
      "mediaUrl": "https://archive.org/download/Norm_Macdonald_Live/Norm%20Macdonald%20Live%20-%20S02E06%20-%20Norm%20Macdonald%20with%20Guest%20Todd%20Glass%20(Part%201).mp4",
      "embedUrl": "https://archive.org/embed/Norm_Macdonald_Live/Norm%20Macdonald%20Live%20-%20S02E06%20-%20Norm%20Macdonald%20with%20Guest%20Todd%20Glass%20(Pt%201).mp4",
      "thumbnail": "https://upload.wikimedia.org/wikipedia/en/2/22/Norm_Macdonald_Live.jpg",
      "tags": [
        "season-2",
        "norm-macdonald-live",
        "Todd Glass (Part 1)"
      ],
      "friendlyTitle": "S2.E6 · Todd Glass Pt. 1",
      "publishedDate": "2014-06-16",
      "fileTitle": "Norm Macdonald Live - S02E06 - Norm Macdonald with Guest Todd Glass (Part 1)",
      "episodeOverall": 18
    },
    {
      "slug": "s2-e7-todd-glass-",
      "guid": "nml-s2-e7-todd-glass-",
      "season": 2,
      "episodeNumber": 7,
      "title": "Todd Glass (Part 2)",
      "guest": "Todd Glass (Part 2)",
      "releaseDate": "2014-06-25",
      "description": "The second part of Norm Macdonald's sit down with Todd Glass.",
      "pageUrl": "https://normmacdonaldarchive.com/nml/s2-e7-todd-glass-",
      "mediaUrl": "https://archive.org/download/Norm_Macdonald_Live/Norm%20Macdonald%20Live%20-%20S02E07%20-%20Norm%20Macdonald%20with%20Guest%20Todd%20Glass%20(Part%202).mp4",
      "embedUrl": "https://archive.org/embed/Norm_Macdonald_Live/Norm%20Macdonald%20Live%20-%20S02E07%20-%20Norm%20Macdonald%20with%20Guest%20Todd%20Glass%20(Pt%202).mp4",
      "thumbnail": "https://upload.wikimedia.org/wikipedia/en/2/22/Norm_Macdonald_Live.jpg",
      "tags": [
        "season-2",
        "norm-macdonald-live",
        "Todd Glass (Part 2)"
      ],
      "friendlyTitle": "S2.E7 · Todd Glass Pt. 2",
      "publishedDate": "2014-06-25",
      "fileTitle": "Norm Macdonald Live - S02E07 - Norm Macdonald with Guest Todd Glass (Part 2)",
      "episodeOverall": 19
    },
    {
      "slug": "s2-e8-bob-saget",
      "guid": "nml-s2-e8-bob-saget",
      "season": 2,
      "episodeNumber": 8,
      "title": "Bob Saget",
      "guest": "Bob Saget",
      "releaseDate": "2014-06-30",
      "description": "Norm is joined by his friend, the beloved comedian Bob Saget.",
      "pageUrl": "https://normmacdonaldarchive.com/nml/s2-e8-bob-saget",
      "mediaUrl": "https://archive.org/download/Norm_Macdonald_Live/Norm%20Macdonald%20Live%20-%20S02E08%20-%20Norm%20Macdonald%20with%20Guest%20Bob%20Saget.mp4",
      "embedUrl": "https://archive.org/embed/Norm_Macdonald_Live/Norm%20Macdonald%20Live%20-%20S02E08%20-%20Norm%20Macdonald%20with%20Guest%20Bob%20Saget.mp4",
      "thumbnail": "https://upload.wikimedia.org/wikipedia/en/2/22/Norm_Macdonald_Live.jpg",
      "tags": [
        "season-2",
        "norm-macdonald-live",
        "Bob Saget"
      ],
      "friendlyTitle": "S2.E8 · Bob Saget",
      "publishedDate": "2014-06-30",
      "fileTitle": "Norm Macdonald Live - S02E08 - Norm Macdonald with Guest Bob Saget",
      "episodeOverall": 20
    },
    {
      "slug": "s2-e9-david-koechner",
      "guid": "nml-s2-e9-david-koechner",
      "season": 2,
      "episodeNumber": 9,
      "title": "David Koechner",
      "guest": "David Koechner",
      "releaseDate": "2014-07-07",
      "description": "Actor and comedian David Koechner, of 'Anchorman' fame, sits down with Norm.",
      "pageUrl": "https://normmacdonaldarchive.com/nml/s2-e9-david-koechner",
      "mediaUrl": "https://archive.org/download/Norm_Macdonald_Live/Norm%20Macdonald%20Live%20-%20S02E09%20-%20Norm%20Macdonald%20with%20Guest%20David%20Koechner.mp4",
      "embedUrl": "https://archive.org/embed/Norm_Macdonald_Live/Norm%20Macdonald%20Live%20-%20S02E09%20-%20Norm%20Macdonald%20with%20Guest%20David%20Koechner.mp4",
      "thumbnail": "https://upload.wikimedia.org/wikipedia/en/2/22/Norm_Macdonald_Live.jpg",
      "tags": [
        "season-2",
        "norm-macdonald-live",
        "David Koechner"
      ],
      "friendlyTitle": "S2.E9 · David Koechner",
      "publishedDate": "2014-07-07",
      "fileTitle": "Norm Macdonald Live - S02E09 - Norm Macdonald with Guest David Koechner",
      "episodeOverall": 21
    },
    {
      "slug": "s2-e10-roseanne-barr",
      "guid": "nml-s2-e10-roseanne-barr",
      "season": 2,
      "episodeNumber": 10,
      "title": "Roseanne Barr",
      "guest": "Roseanne Barr",
      "releaseDate": "2014-07-14",
      "description": "A candid and fascinating interview with television icon Roseanne Barr.",
      "pageUrl": "https://normmacdonaldarchive.com/nml/s2-e10-roseanne-barr",
      "mediaUrl": "https://archive.org/download/Norm_Macdonald_Live/Norm%20Macdonald%20Live%20-%20S02E10%20-%20Norm%20Macdonald%20with%20Guest%20Roseanne%20Barr.mp4",
      "embedUrl": "https://archive.org/embed/Norm_Macdonald_Live/Norm%20Macdonald%20Live%20-%20S02E10%20-%20Norm%20Macdonald%20with%20Guest%20Roseanne%20Barr.mp4",
      "thumbnail": "https://upload.wikimedia.org/wikipedia/en/2/22/Norm_Macdonald_Live.jpg",
      "tags": [
        "season-2",
        "norm-macdonald-live",
        "Roseanne Barr"
      ],
      "friendlyTitle": "S2.E10 · Roseanne Barr",
      "publishedDate": "2014-07-14",
      "fileTitle": "Norm Macdonald Live - S02E10 - Norm Macdonald with Guest Roseanne Barr",
      "episodeOverall": 22
    },
    {
      "slug": "s2-e11-marc-maron",
      "guid": "nml-s2-e11-marc-maron",
      "season": 2,
      "episodeNumber": 11,
      "title": "Marc Maron",
      "guest": "Marc Maron",
      "releaseDate": "2014-07-21",
      "description": "Fellow comedian and podcasting pioneer Marc Maron joins the show.",
      "pageUrl": "https://normmacdonaldarchive.com/nml/s2-e11-marc-maron",
      "mediaUrl": "https://archive.org/download/Norm_Macdonald_Live/Norm%20Macdonald%20Live%20-%20S02E11%20-%20Norm%20Macdonald%20with%20Guest%20Marc%20Maron.mp4",
      "embedUrl": "https://archive.org/embed/Norm_Macdonald_Live/Norm%20Macdonald%20Live%20-%20S02E11%20-%20Norm%20Macdonald%20with%20Guest%20Marc%20Maron.mp4",
      "thumbnail": "https://upload.wikimedia.org/wikipedia/en/2/22/Norm_Macdonald_Live.jpg",
      "tags": [
        "season-2",
        "norm-macdonald-live",
        "Marc Maron"
      ],
      "friendlyTitle": "S2.E11 · Marc Maron",
      "publishedDate": "2014-07-21",
      "fileTitle": "Norm Macdonald Live - S02E11 - Norm Macdonald with Guest Marc Maron",
      "episodeOverall": 23
    },
    {
      "slug": "s2-e12-martin-mull",
      "guid": "nml-s2-e12-martin-mull",
      "season": 2,
      "episodeNumber": 12,
      "title": "Martin Mull",
      "guest": "Martin Mull",
      "releaseDate": "2014-07-28",
      "description": "The multi-talented actor, comedian, and musician Martin Mull has a chat with Norm.",
      "pageUrl": "https://normmacdonaldarchive.com/nml/s2-e12-martin-mull",
      "mediaUrl": "https://archive.org/download/Norm_Macdonald_Live/Norm%20Macdonald%20Live%20-%20S02E12%20-%20Norm%20Macdonald%20with%20Guest%20Martin%20Mull.mp4",
      "embedUrl": "https://archive.org/embed/Norm_Macdonald_Live/Norm%20Macdonald%20Live%20-%20S02E12%20-%20Norm%20Macdonald%20with%20Guest%20Martin%20Mull.mp4",
      "thumbnail": "https://upload.wikimedia.org/wikipedia/en/2/22/Norm_Macdonald_Live.jpg",
      "tags": [
        "season-2",
        "norm-macdonald-live",
        "Martin Mull"
      ],
      "friendlyTitle": "S2.E12 · Martin Mull",
      "publishedDate": "2014-07-28",
      "fileTitle": "Norm Macdonald Live - S02E12 - Norm Macdonald with Guest Martin Mull",
      "episodeOverall": 24
    },
    {
      "slug": "s2-e13-jack-carter",
      "guid": "nml-s2-e13-jack-carter",
      "season": 2,
      "episodeNumber": 13,
      "title": "Jack Carter",
      "guest": "Jack Carter",
      "releaseDate": "2014-08-07",
      "description": "A talk with legendary comedian and actor of early television, Jack Carter.",
      "pageUrl": "https://normmacdonaldarchive.com/nml/s2-e13-jack-carter",
      "mediaUrl": "https://archive.org/download/Norm_Macdonald_Live/Norm%20Macdonald%20Live%20-%20S02E13%20-%20Norm%20Macdonald%20with%20Guest%20Jack%20Carter.mp4",
      "embedUrl": "https://archive.org/embed/Norm_Macdonald_Live/Norm%20Macdonald%20Live%20-%20S02E13%20-%20Norm%20Macdonald%20with%20Guest%20Jack%20Carter.mp4",
      "thumbnail": "https://upload.wikimedia.org/wikipedia/en/2/22/Norm_Macdonald_Live.jpg",
      "tags": [
        "season-2",
        "norm-macdonald-live",
        "Jack Carter"
      ],
      "friendlyTitle": "S2.E13 · Jack Carter",
      "publishedDate": "2014-08-07",
      "fileTitle": "Norm Macdonald Live - S02E13 - Norm Macdonald with Guest Jack Carter",
      "episodeOverall": 25
    },
    {
      "slug": "s3-e1-stephen-merchant",
      "guid": "nml-s3-e1-stephen-merchant",
      "season": 3,
      "episodeNumber": 1,
      "title": "Stephen Merchant",
      "guest": "Stephen Merchant",
      "releaseDate": "2016-09-15",
      "description": "Season 3 begins with the co-creator of 'The Office,' Stephen Merchant.",
      "pageUrl": "https://normmacdonaldarchive.com/nml/s3-e1-stephen-merchant",
      "mediaUrl": "https://archive.org/download/Norm_Macdonald_Live/Norm%20Macdonald%20Live%20-%20S03E01%20-%20Norm%20Macdonald%20with%20Guest%20Stephen%20Merchant.mp4",
      "embedUrl": "https://archive.org/embed/Norm_Macdonald_Live/Norm%20Macdonald%20Live%20-%20S03E01%20-%20Norm%20Macdonald%20with%20Guest%20Stephen%20Merchant.mp4",
      "thumbnail": "https://upload.wikimedia.org/wikipedia/en/2/22/Norm_Macdonald_Live.jpg",
      "tags": [
        "season-3",
        "norm-macdonald-live",
        "Stephen Merchant"
      ],
      "friendlyTitle": "S3.E1 · Stephen Merchant",
      "publishedDate": "2016-09-15",
      "fileTitle": "Norm Macdonald Live - S03E01 - Norm Macdonald with Guest Stephen Merchant",
      "episodeOverall": 26
    },
    {
      "slug": "s3-e2-bill-hader",
      "guid": "nml-s3-e2-bill-hader",
      "season": 3,
      "episodeNumber": 2,
      "title": "Bill Hader",
      "guest": "Bill Hader",
      "releaseDate": "2016-09-26",
      "description": "SNL standout and 'Barry' creator Bill Hader joins Norm for a hilarious conversation.",
      "pageUrl": "https://normmacdonaldarchive.com/nml/s3-e2-bill-hader",
      "mediaUrl": "https://archive.org/download/Norm_Macdonald_Live/Norm%20Macdonald%20Live%20-%20S03E02%20-%20Norm%20Macdonald%20with%20Guest%20Bill%20Hader.mp4",
      "embedUrl": "https://archive.org/embed/Norm_Macdonald_Live/Norm%20Macdonald%20Live%20-%20S03E02%20-%20Norm%20Macdonald%20with%20Guest%20Bill%20Hader.mp4",
      "thumbnail": "https://upload.wikimedia.org/wikipedia/en/2/22/Norm_Macdonald_Live.jpg",
      "tags": [
        "season-3",
        "norm-macdonald-live",
        "Bill Hader"
      ],
      "friendlyTitle": "S3.E2 · Bill Hader",
      "publishedDate": "2016-09-26",
      "fileTitle": "Norm Macdonald Live - S03E02 - Norm Macdonald with Guest Bill Hader",
      "episodeOverall": 27
    },
    {
      "slug": "s3-e3-david-letterman",
      "guid": "nml-s3-e3-david-letterman",
      "season": 3,
      "episodeNumber": 3,
      "title": "David Letterman",
      "guest": "David Letterman",
      "releaseDate": "2017-07-25",
      "description": "Norm sits down with his hero and late-night television icon, David Letterman.",
      "pageUrl": "https://normmacdonaldarchive.com/nml/s3-e3-david-letterman",
      "mediaUrl": "https://archive.org/download/Norm_Macdonald_Live/Norm%20Macdonald%20Live%20-%20S03E03%20-%20Norm%20Macdonald%20with%20Guest%20David%20Letterman.mp4",
      "embedUrl": "https://archive.org/embed/Norm_Macdonald_Live/Norm%20Macdonald%20Live%20-%20S03E03%20-%20Norm%20Macdonald%20with%20Guest%20David%20Letterman.mp4",
      "thumbnail": "https://upload.wikimedia.org/wikipedia/en/2/22/Norm_Macdonald_Live.jpg",
      "tags": [
        "season-3",
        "norm-macdonald-live",
        "David Letterman"
      ],
      "friendlyTitle": "S3.E3 · David Letterman",
      "publishedDate": "2017-07-25",
      "fileTitle": "Norm Macdonald Live - S03E03 - Norm Macdonald with Guest David Letterman",
      "episodeOverall": 28
    },
    {
      "slug": "s3-e4-mike-tyson",
      "guid": "nml-s3-e4-mike-tyson",
      "season": 3,
      "episodeNumber": 4,
      "title": "Mike Tyson",
      "guest": "Mike Tyson",
      "releaseDate": "2017-08-01",
      "description": "A surprisingly insightful and funny interview with boxing legend Mike Tyson.",
      "pageUrl": "https://normmacdonaldarchive.com/nml/s3-e4-mike-tyson",
      "mediaUrl": "https://archive.org/download/Norm_Macdonald_Live/Norm%20Macdonald%20Live%20-%20S03E04%20-%20Norm%20Macdonald%20with%20Guest%20Mike%20Tyson.mp4",
      "embedUrl": "https://archive.org/embed/Norm_Macdonald_Live/Norm%20Macdonald%20Live%20-%20S03E04%20-%20Norm%20Macdonald%20with%20Guest%20Mike%20Tyson.mp4",
      "thumbnail": "https://upload.wikimedia.org/wikipedia/en/2/22/Norm_Macdonald_Live.jpg",
      "tags": [
        "season-3",
        "norm-macdonald-live",
        "Mike Tyson"
      ],
      "friendlyTitle": "S3.E4 · Mike Tyson",
      "publishedDate": "2017-08-01",
      "fileTitle": "Norm Macdonald Live - S03E04 - Norm Macdonald with Guest Mike Tyson",
      "episodeOverall": 29
    },
    {
      "slug": "s3-e5-bobby-lee",
      "guid": "nml-s3-e5-bobby-lee",
      "season": 3,
      "episodeNumber": 5,
      "title": "Bobby Lee",
      "guest": "Bobby Lee",
      "releaseDate": "2017-08-08",
      "description": "Comedian and 'MADtv' alumnus Bobby Lee joins the show.",
      "pageUrl": "https://normmacdonaldarchive.com/nml/s3-e5-bobby-lee",
      "mediaUrl": "https://archive.org/download/Norm_Macdonald_Live/Norm%20Macdonald%20Live%20-%20S03E05%20-%20Norm%20Macdonald%20with%20Guest%20Bobby%20Lee.mp4",
      "embedUrl": "https://archive.org/embed/Norm_Macdonald_Live/Norm%20Macdonald%20Live%20-%20S03E05%20-%20Norm%20Macdonald%20with%20Guest%20Bobby%20Lee.mp4",
      "thumbnail": "https://upload.wikimedia.org/wikipedia/en/2/22/Norm_Macdonald_Live.jpg",
      "tags": [
        "season-3",
        "norm-macdonald-live",
        "Bobby Lee"
      ],
      "friendlyTitle": "S3.E5 · Bobby Lee",
      "publishedDate": "2017-08-08",
      "fileTitle": "Norm Macdonald Live - S03E05 - Norm Macdonald with Guest Bobby Lee",
      "episodeOverall": 30
    },
    {
      "slug": "s3-e6-sarah-silverman-",
      "guid": "nml-s3-e6-sarah-silverman-",
      "season": 3,
      "episodeNumber": 6,
      "title": "Sarah Silverman (Part 1)",
      "guest": "Sarah Silverman (Part 1)",
      "releaseDate": "2017-08-15",
      "description": "The first part of Norm Macdonald's sit down with Sarah Silverman.",
      "pageUrl": "https://normmacdonaldarchive.com/nml/s3-e6-sarah-silverman-",
      "mediaUrl": "https://archive.org/download/Norm_Macdonald_Live/Norm%20Macdonald%20Live%20-%20S03E06%20-%20Norm%20Macdonald%20with%20Guest%20Sarah%20Silverman%20(Part%201).mp4",
      "embedUrl": "https://archive.org/embed/Norm_Macdonald_Live/Norm%20Macdonald%20Live%20-%20S03E06%20-%20Norm%20Macdonald%20with%20Guest%20Sarah%20Silverman%20(Pt%201).mp4",
      "thumbnail": "https://upload.wikimedia.org/wikipedia/en/2/22/Norm_Macdonald_Live.jpg",
      "tags": [
        "season-3",
        "norm-macdonald-live",
        "Sarah Silverman (Part 1)"
      ],
      "friendlyTitle": "S3.E6 · Sarah Silverman Pt. 1",
      "publishedDate": "2017-08-15",
      "fileTitle": "Norm Macdonald Live - S03E06 - Norm Macdonald with Guest Sarah Silverman (Part 1)",
      "episodeOverall": 31
    },
    {
      "slug": "s3-e7-sarah-silverman-",
      "guid": "nml-s3-e7-sarah-silverman-",
      "season": 3,
      "episodeNumber": 7,
      "title": "Sarah Silverman (Part 2)",
      "guest": "Sarah Silverman (Part 2)",
      "releaseDate": "2017-08-15",
      "description": "The second part of Norm Macdonald's sit down with Sarah Silverman.",
      "pageUrl": "https://normmacdonaldarchive.com/nml/s3-e7-sarah-silverman-",
      "mediaUrl": "https://archive.org/download/Norm_Macdonald_Live/Norm%20Macdonald%20Live%20-%20S03E07%20-%20Norm%20Macdonald%20with%20Guest%20Sarah%20Silverman%20(Part%202).mp4",
      "embedUrl": "https://archive.org/embed/Norm_Macdonald_Live/Norm%20Macdonald%20Live%20-%20S03E07%20-%20Norm%20Macdonald%20with%20Guest%20Sarah%20Silverman%20(Pt%202).mp4",
      "thumbnail": "https://upload.wikimedia.org/wikipedia/en/2/22/Norm_Macdonald_Live.jpg",
      "tags": [
        "season-3",
        "norm-macdonald-live",
        "Sarah Silverman (Part 2)"
      ],
      "friendlyTitle": "S3.E7 · Sarah Silverman Pt. 2",
      "publishedDate": "2017-08-15",
      "fileTitle": "Norm Macdonald Live - S03E07 - Norm Macdonald with Guest Sarah Silverman (Part 2)",
      "episodeOverall": 32
    },
    {
      "slug": "s3-e8-dana-carvey",
      "guid": "nml-s3-e8-dana-carvey",
      "season": 3,
      "episodeNumber": 8,
      "title": "Dana Carvey",
      "guest": "Dana Carvey",
      "releaseDate": "2017-08-22",
      "description": "Fellow SNL legend and master impressionist Dana Carvey sits down with Norm.",
      "pageUrl": "https://normmacdonaldarchive.com/nml/s3-e8-dana-carvey",
      "mediaUrl": "https://archive.org/download/Norm_Macdonald_Live/Norm%20Macdonald%20Live%20-%20S03E08%20-%20Norm%20Macdonald%20with%20Guest%20Dana%20Carvey.mp4",
      "embedUrl": "https://archive.org/embed/Norm_Macdonald_Live/Norm%20Macdonald%20Live%20-%20S03E08%20-%20Norm%20Macdonald%20with%20Guest%20Dana%20Carvey.mp4",
      "thumbnail": "https://upload.wikimedia.org/wikipedia/en/2/22/Norm_Macdonald_Live.jpg",
      "tags": [
        "season-3",
        "norm-macdonald-live",
        "Dana Carvey"
      ],
      "friendlyTitle": "S3.E8 · Dana Carvey",
      "publishedDate": "2017-08-22",
      "fileTitle": "Norm Macdonald Live - S03E08 - Norm Macdonald with Guest Dana Carvey",
      "episodeOverall": 33
    },
    {
      "slug": "s3-e9-jerry-seinfeld",
      "guid": "nml-s3-e9-jerry-seinfeld",
      "season": 3,
      "episodeNumber": 9,
      "title": "Jerry Seinfeld",
      "guest": "Jerry Seinfeld",
      "releaseDate": "2017-08-29",
      "description": "A must-see conversation about comedy with the one and only Jerry Seinfeld.",
      "pageUrl": "https://normmacdonaldarchive.com/nml/s3-e9-jerry-seinfeld",
      "mediaUrl": "https://archive.org/download/Norm_Macdonald_Live/Norm%20Macdonald%20Live%20-%20S03E09%20-%20Norm%20Macdonald%20with%20Guest%20Jerry%20Seinfeld.mp4",
      "embedUrl": "https://archive.org/embed/Norm_Macdonald_Live/Norm%20Macdonald%20Live%20-%20S03E09%20-%20Norm%20Macdonald%20with%20Guest%20Jerry%20Seinfeld.mp4",
      "thumbnail": "https://upload.wikimedia.org/wikipedia/en/2/22/Norm_Macdonald_Live.jpg",
      "tags": [
        "season-3",
        "norm-macdonald-live",
        "Jerry Seinfeld"
      ],
      "friendlyTitle": "S3.E9 · Jerry Seinfeld",
      "publishedDate": "2017-08-29",
      "fileTitle": "Norm Macdonald Live - S03E09 - Norm Macdonald with Guest Jerry Seinfeld",
      "episodeOverall": 34
    },
    {
      "slug": "s3-e10-caitlyn-jenner",
      "guid": "nml-s3-e10-caitlyn-jenner",
      "season": 3,
      "episodeNumber": 10,
      "title": "Caitlyn Jenner",
      "guest": "Caitlyn Jenner",
      "releaseDate": "2017-09-05",
      "description": "A respectful and surprisingly funny interview with Caitlyn Jenner.",
      "pageUrl": "https://normmacdonaldarchive.com/nml/s3-e10-caitlyn-jenner",
      "mediaUrl": "https://archive.org/download/Norm_Macdonald_Live/Norm%20Macdonald%20Live%20-%20S03E10%20-%20Norm%20Macdonald%20with%20Guest%20Caitlyn%20Jenner.mp4",
      "embedUrl": "https://archive.org/embed/Norm_Macdonald_Live/Norm%20Macdonald%20Live%20-%20S03E10%20-%20Norm%20Macdonald%20with%20Guest%20Caitlyn%20Jenner.mp4",
      "thumbnail": "https://upload.wikimedia.org/wikipedia/en/2/22/Norm_Macdonald_Live.jpg",
      "tags": [
        "season-3",
        "norm-macdonald-live",
        "Caitlyn Jenner"
      ],
      "friendlyTitle": "S3.E10 · Caitlyn Jenner",
      "publishedDate": "2017-09-05",
      "fileTitle": "Norm Macdonald Live - S03E10 - Norm Macdonald with Guest Caitlyn Jenner",
      "episodeOverall": 35
    },
    {
      "slug": "s3-e11-rich-little",
      "guid": "nml-s3-e11-rich-little",
      "season": 3,
      "episodeNumber": 11,
      "title": "Rich Little",
      "guest": "Rich Little",
      "releaseDate": "2017-09-12",
      "description": "Norm talks with the legendary impressionist and Las Vegas icon, Rich Little.",
      "pageUrl": "https://normmacdonaldarchive.com/nml/s3-e11-rich-little",
      "mediaUrl": "https://archive.org/download/Norm_Macdonald_Live/Norm%20Macdonald%20Live%20-%20S03E11%20-%20Norm%20Macdonald%20with%20Guest%20Rich%20Little.mp4",
      "embedUrl": "https://archive.org/embed/Norm_Macdonald_Live/Norm%20Macdonald%20Live%20-%20S03E11%20-%20Norm%20Macdonald%20with%20Guest%20Rich%20Little.mp4",
      "thumbnail": "https://upload.wikimedia.org/wikipedia/en/2/22/Norm_Macdonald_Live.jpg",
      "tags": [
        "season-3",
        "norm-macdonald-live",
        "Rich Little"
      ],
      "friendlyTitle": "S3.E11 · Rich Little",
      "publishedDate": "2017-09-12",
      "fileTitle": "Norm Macdonald Live - S03E11 - Norm Macdonald with Guest Rich Little",
      "episodeOverall": 36
    },
    {
      "slug": "s3-e12-margaret-cho",
      "guid": "nml-s3-e12-margaret-cho",
      "season": 3,
      "episodeNumber": 12,
      "title": "Margaret Cho",
      "guest": "Margaret Cho",
      "releaseDate": "2017-09-19",
      "description": "Comedian and actress Margaret Cho joins Norm for a candid conversation.",
      "pageUrl": "https://normmacdonaldarchive.com/nml/s3-e12-margaret-cho",
      "mediaUrl": "https://archive.org/download/Norm_Macdonald_Live/Norm%20Macdonald%20Live%20-%20S03E12%20-%20Norm%20Macdonald%20with%20Guest%20Margaret%20Cho.mp4",
      "embedUrl": "https://archive.org/embed/Norm_Macdonald_Live/Norm%20Macdonald%20Live%20-%20S03E12%20-%20Norm%20Macdonald%20with%20Guest%20Margaret%20Cho.mp4",
      "thumbnail": "https://upload.wikimedia.org/wikipedia/en/2/22/Norm_Macdonald_Live.jpg",
      "tags": [
        "season-3",
        "norm-macdonald-live",
        "Margaret Cho"
      ],
      "friendlyTitle": "S3.E12 · Margaret Cho",
      "publishedDate": "2017-09-19",
      "fileTitle": "Norm Macdonald Live - S03E12 - Norm Macdonald with Guest Margaret Cho",
      "episodeOverall": 37
    },
    {
      "slug": "s3-e13-tim-allen",
      "guid": "nml-s3-e13-tim-allen",
      "season": 3,
      "episodeNumber": 13,
      "title": "Tim Allen",
      "guest": "Tim Allen",
      "releaseDate": "2017-09-26",
      "description": "Sitcom star and comedian Tim Allen sits down with Norm.",
      "pageUrl": "https://normmacdonaldarchive.com/nml/s3-e13-tim-allen",
      "mediaUrl": "https://archive.org/download/Norm_Macdonald_Live/Norm%20Macdonald%20Live%20-%20S03E13%20-%20Norm%20Macdonald%20with%20Guest%20Tim%20Allen.mp4",
      "embedUrl": "https://archive.org/embed/Norm_Macdonald_Live/Norm%20Macdonald%20Live%20-%20S03E13%20-%20Norm%20Macdonald%20with%20Guest%20Tim%20Allen.mp4",
      "thumbnail": "https://upload.wikimedia.org/wikipedia/en/2/22/Norm_Macdonald_Live.jpg",
      "tags": [
        "season-3",
        "norm-macdonald-live",
        "Tim Allen"
      ],
      "friendlyTitle": "S3.E13 · Tim Allen",
      "publishedDate": "2017-09-26",
      "fileTitle": "Norm Macdonald Live - S03E13 - Norm Macdonald with Guest Tim Allen",
      "episodeOverall": 38
    },
    {
      "slug": "s3-e14-jim-carrey",
      "guid": "nml-s3-e14-jim-carrey",
      "season": 3,
      "episodeNumber": 14,
      "title": "Jim Carrey",
      "guest": "Jim Carrey",
      "releaseDate": "2017-10-03",
      "description": "A fascinating and philosophical conversation with comedy superstar Jim Carrey.",
      "pageUrl": "https://normmacdonaldarchive.com/nml/s3-e14-jim-carrey",
      "mediaUrl": "https://archive.org/download/Norm_Macdonald_Live/Norm%20Macdonald%20Live%20-%20S03E14%20-%20Norm%20Macdonald%20with%20Guest%20Jim%20Carrey.mp4",
      "embedUrl": "https://archive.org/embed/Norm_Macdonald_Live/Norm%20Macdonald%20Live%20-%20S03E14%20-%20Norm%20Macdonald%20with%20Guest%20Jim%20Carrey.mp4",
      "thumbnail": "https://upload.wikimedia.org/wikipedia/en/2/22/Norm_Macdonald_Live.jpg",
      "tags": [
        "season-3",
        "norm-macdonald-live",
        "Jim Carrey"
      ],
      "friendlyTitle": "S3.E14 · Jim Carrey",
      "publishedDate": "2017-10-03",
      "fileTitle": "Norm Macdonald Live - S03E14 - Norm Macdonald with Guest Jim Carrey",
      "episodeOverall": 39
    }
  ]
}
